{"Overrides":{"0":1,"18":0,"2":10,"27":8,"42":5,"43":10,"45":0,"54":0,"57":0,"66":0,"69":0,"76":5,"78":0},"BoxLabels":{"0":[{"X":313,"Y":202,"S":10},{"X":310,"Y":221,"S":10},{"X":306,"Y":219,"S":20},{"X":314,"Y":175,"S":20},{"X":311,"Y":203,"S":20},{"X":306,"Y":188,"S":20},{"X":89,"Y":267,"S":20},{"X":135,"Y":268,"S":20},{"X":7,"Y":203,"S":20},{"X":2,"Y":209,"S":20},{"X":1,"Y":185,"S":20},{"X":6,"Y":239,"S":20},{"X":7,"Y":223,"S":20},{"X":10,"Y":235,"S":20},{"X":105,"Y":226,"S":20},{"X":58,"Y":226,"S":20},{"X":59,"Y":252,"S":60},{"X":104,"Y":252,"S":60},{"X":139,"Y":268,"S":60},{"X":170,"Y":270,"S":60},{"X":46,"Y":278,"S":60},{"X":72,"Y":283,"S":60},{"X":421,"Y":191,"S":30},{"X":451,"Y":197,"S":30},{"X":473,"Y":191,"S":30},{"X":501,"Y":191,"S":30},{"X":561,"Y":177,"S":30},{"X":360,"Y":181,"S":30},{"X":351,"Y":178,"S":30},{"X":2,"Y":168,"S":30}],"1":[{"X":407,"Y":162,"S":10},{"X":421,"Y":162,"S":10},{"X":412,"Y":162,"S":10},{"X":410,"Y":164,"S":10},{"X":424,"Y":163,"S":10},{"X":443,"Y":165,"S":10},{"X":432,"Y":163,"S":10},{"X":443,"Y":164,"S":10},{"X":484,"Y":165,"S":10},{"X":489,"Y":163,"S":10},{"X":550,"Y":156,"S":10}],"2":[{"X":557,"Y":145,"S":20},{"X":556,"Y":124,"S":20},{"X":558,"Y":114,"S":10},{"X":277,"Y":94,"S":10},{"X":281,"Y":93,"S":10},{"X":270,"Y":75,"S":10},{"X":263,"Y":73,"S":10},{"X":273,"Y":71,"S":10},{"X":263,"Y":70,"S":10},{"X":279,"Y":89,"S":10},{"X":323,"Y":115,"S":10},{"X":323,"Y":107,"S":10},{"X":302,"Y":148,"S":10},{"X":301,"Y":146,"S":10},{"X":301,"Y":136,"S":10},{"X":352,"Y":109,"S":10},{"X":549,"Y":151,"S":10},{"X":550,"Y":152,"S":10},{"X":550,"Y":155,"S":10}],"5":[{"X":228,"Y":161,"S":10},{"X":230,"Y":151,"S":10},{"X":228,"Y":154,"S":10},{"X":232,"Y":167,"S":10},{"X":229,"Y":170,"S":10},{"X":236,"Y":161,"S":10}],"8":[{"X":573,"Y":139,"S":10},{"X":590,"Y":143,"S":10},{"X":585,"Y":142,"S":10},{"X":577,"Y":145,"S":10},{"X":571,"Y":145,"S":10},{"X":589,"Y":147,"S":10},{"X":577,"Y":147,"S":10},{"X":573,"Y":120,"S":10},{"X":571,"Y":105,"S":10},{"X":569,"Y":114,"S":10},{"X":574,"Y":109,"S":10},{"X":577,"Y":109,"S":10},{"X":561,"Y":107,"S":10},{"X":582,"Y":118,"S":10},{"X":582,"Y":117,"S":10},{"X":571,"Y":124,"S":10},{"X":572,"Y":135,"S":10},{"X":570,"Y":136,"S":10}]}}